syvlib/__init__.py
syvlib/codec.py
syvlib/cycle.py
syvlib/drop.py
syvlib/renew_thread.py
syvlib/scoped_session.py
syvlib/session.py
syvlib-0.2.150.dist-info/LICENSE.md
syvlib-0.2.150.dist-info/METADATA
syvlib-0.2.150.dist-info/WHEEL
syvlib-0.2.150.dist-info/top_level.txt
syvlib-0.2.150.dist-info/zip-safe
syvlib-0.2.150.dist-info/RECORD
